<?xml version="1.0" encoding="UTF-8"?><record_update sys_domain="global" table="sys_ux_page_property">
    <sys_ux_page_property action="DELETE">
        <choices/>
        <description>Tabs Configuration</description>
        <name>chrome_tab</name>
        <page display_value="eSO Mockup">1a69e2c1acadd21076135e9dc612d3a1</page>
        <required_translations>[ {
  "message" : "New Sales Order Items",
  "comment" : ""
}, {
  "message" : "New eSO Approval",
  "comment" : ""
} ]</required_translations>
        <route/>
        <suffix/>
        <sys_class_name>sys_ux_page_property</sys_class_name>
        <sys_created_by>admin</sys_created_by>
        <sys_created_on>2024-10-28 05:07:08</sys_created_on>
        <sys_domain>global</sys_domain>
        <sys_domain_path>global</sys_domain_path>
        <sys_id>5669e2c16cadd210699eaea1ff3c0592</sys_id>
        <sys_mod_count>1</sys_mod_count>
        <sys_name>chrome_tab</sys_name>
        <sys_package display_value="eSO Mockup" source="x_1040502_eso_mo_0">2a930f88c3211210945e9e1d05013139</sys_package>
        <sys_policy/>
        <sys_scope display_value="eSO Mockup">2a930f88c3211210945e9e1d05013139</sys_scope>
        <sys_update_name>sys_ux_page_property_5669e2c16cadd210699eaea1ff3c0592</sys_update_name>
        <sys_updated_by>admin</sys_updated_by>
        <sys_updated_on>2024-10-28 05:07:16</sys_updated_on>
        <type>json</type>
        <unique_name>x_1040502_eso_mo_0.1a69e2c1acadd21076135e9dc612d3a1.root.global.chrome_tab</unique_name>
        <value>{"contextual":["record"],"newTabMenu":[{"label":{"translatable":true,"message":"New eSO Approval"},"routeInfo":{"route":"record","fields":{"table":"x_1040502_eso_mo_0_eso_approval","sysId":"-1"},"multiInstField":"sysId"},"condition":{"tableDescription":{"table":"x_1040502_eso_mo_0_eso_approval","canCreate":true}}},{"label":{"translatable":true,"message":"New Sales Order Items"},"routeInfo":{"route":"record","fields":{"table":"x_1040502_eso_mo_0_sales_order_items","sysId":"-1"},"multiInstField":"sysId"},"condition":{"tableDescription":{"table":"x_1040502_eso_mo_0_sales_order_items","canCreate":true}}}],"maxMainTabLimit":10,"maxTotalSubTabLimit":30}</value>
    </sys_ux_page_property>
    <sys_translated_text action="DELETE" query="documentkey=5669e2c16cadd210699eaea1ff3c0592"/>
    <sys_update_version action="INSERT_OR_UPDATE">
        <action>DELETE</action>
        <application display_value="eSO Mockup">2a930f88c3211210945e9e1d05013139</application>
        <file_path/>
        <instance_id>cca3323adb1a71542f082a5913961937</instance_id>
        <instance_name>dev208145</instance_name>
        <name>sys_ux_page_property_5669e2c16cadd210699eaea1ff3c0592</name>
        <payload><![CDATA[<?xml version="1.0" encoding="UTF-8"?><record_update sys_domain="global" table="sys_ux_page_property"><sys_ux_page_property action="INSERT_OR_UPDATE"><choices/><description>Tabs Configuration</description><name>chrome_tab</name><page display_value="eSO Mockup">1a69e2c1acadd21076135e9dc612d3a1</page><required_translations>[ {
  "message" : "New Sales Order Items",
  "comment" : ""
}, {
  "message" : "New eSO Approval",
  "comment" : ""
} ]</required_translations><route/><suffix/><sys_class_name>sys_ux_page_property</sys_class_name><sys_created_by>admin</sys_created_by><sys_created_on>2024-10-28 05:07:08</sys_created_on><sys_domain>global</sys_domain><sys_domain_path>global</sys_domain_path><sys_id>5669e2c16cadd210699eaea1ff3c0592</sys_id><sys_mod_count>1</sys_mod_count><sys_name>chrome_tab</sys_name><sys_package display_value="eSO Mockup" source="x_1040502_eso_mo_0">2a930f88c3211210945e9e1d05013139</sys_package><sys_policy/><sys_scope display_value="eSO Mockup">2a930f88c3211210945e9e1d05013139</sys_scope><sys_update_name>sys_ux_page_property_5669e2c16cadd210699eaea1ff3c0592</sys_update_name><sys_updated_by>admin</sys_updated_by><sys_updated_on>2024-10-28 05:07:16</sys_updated_on><type>json</type><unique_name>x_1040502_eso_mo_0.1a69e2c1acadd21076135e9dc612d3a1.root.global.chrome_tab</unique_name><value>{"contextual":["record"],"newTabMenu":[{"label":{"translatable":true,"message":"New eSO Approval"},"routeInfo":{"route":"record","fields":{"table":"x_1040502_eso_mo_0_eso_approval","sysId":"-1"},"multiInstField":"sysId"},"condition":{"tableDescription":{"table":"x_1040502_eso_mo_0_eso_approval","canCreate":true}}},{"label":{"translatable":true,"message":"New Sales Order Items"},"routeInfo":{"route":"record","fields":{"table":"x_1040502_eso_mo_0_sales_order_items","sysId":"-1"},"multiInstField":"sysId"},"condition":{"tableDescription":{"table":"x_1040502_eso_mo_0_sales_order_items","canCreate":true}}}],"maxMainTabLimit":10,"maxTotalSubTabLimit":30}</value></sys_ux_page_property><sys_translated_text action="delete_multiple" query="documentkey=5669e2c16cadd210699eaea1ff3c0592"/></record_update>]]></payload>
        <payload_hash>900412137</payload_hash>
        <record_name>chrome_tab</record_name>
        <reverted_from/>
        <source>2e930f88c3211210945e9e1d05013188</source>
        <source_table>sys_update_set</source_table>
        <state>previous</state>
        <sys_created_by>admin</sys_created_by>
        <sys_created_on>2024-10-28 05:07:16</sys_created_on>
        <sys_id>6479e6c1c3add210945e9e1d05013190</sys_id>
        <sys_mod_count>0</sys_mod_count>
        <sys_recorded_at>192d18571d70000001</sys_recorded_at>
        <sys_updated_by>admin</sys_updated_by>
        <sys_updated_on>2024-10-28 05:07:16</sys_updated_on>
        <type>UX Page Property</type>
        <update_guid>2c79e6c1cdadd210744397a5535e338f</update_guid>
        <update_guid_history>2c79e6c1cdadd210744397a5535e338f:900412137,2479e6c132add2107280c13cd8b9d48e:25056504</update_guid_history>
    </sys_update_version>
    <sys_metadata_delete action="INSERT_OR_UPDATE">
        <sys_audit_delete/>
        <sys_class_name>sys_metadata_delete</sys_class_name>
        <sys_created_by>admin</sys_created_by>
        <sys_created_on>2024-10-29 07:56:32</sys_created_on>
        <sys_db_object display_value="" name="sys_ux_page_property">sys_ux_page_property</sys_db_object>
        <sys_id>65897d725b014e6e957696576696d5a4</sys_id>
        <sys_metadata>5669e2c16cadd210699eaea1ff3c0592</sys_metadata>
        <sys_mod_count>0</sys_mod_count>
        <sys_name>chrome_tab</sys_name>
        <sys_package display_value="eSO Mockup" source="x_1040502_eso_mo_0">2a930f88c3211210945e9e1d05013139</sys_package>
        <sys_parent/>
        <sys_policy/>
        <sys_scope display_value="eSO Mockup">2a930f88c3211210945e9e1d05013139</sys_scope>
        <sys_scope_delete display_value="">6320d1d0585d49868d4040a883e3a879</sys_scope_delete>
        <sys_update_name>sys_ux_page_property_5669e2c16cadd210699eaea1ff3c0592</sys_update_name>
        <sys_update_version display_value="sys_ux_page_property_5669e2c16cadd210699eaea1ff3c0592">6479e6c1c3add210945e9e1d05013190</sys_update_version>
        <sys_updated_by>admin</sys_updated_by>
        <sys_updated_on>2024-10-29 07:56:32</sys_updated_on>
    </sys_metadata_delete>
</record_update>
